front/__init__.py
front/api.py
front/exceptions.py
front/fields.py
front/mixins.py
front/models.py
front/search.py
front/util.py
py_front-0.0.5.dist-info/LICENSE
py_front-0.0.5.dist-info/METADATA
py_front-0.0.5.dist-info/WHEEL
py_front-0.0.5.dist-info/top_level.txt
py_front-0.0.5.dist-info/zip-safe
py_front-0.0.5.dist-info/RECORD
